active_core/ObjectWorker.py
active_core/__init__.py
active_core/analyzer.py
active_core/worker.py
auxiliary/__init__.py
auxiliary/interfaces.py
auxiliary/standards.py
auxiliary/utils.py
message_broker_interface-0.1.dist-info/METADATA
message_broker_interface-0.1.dist-info/RECORD
message_broker_interface-0.1.dist-info/WHEEL
message_broker_interface-0.1.dist-info/top_level.txt
