Metadata-Version: 2.1
Name: message-broker-interface
Version: 0.1
Summary: Provides the basic glue for some message broker based projects
Home-page: https://github.com/ihgalis/message_broker_interface
Author: Andre Fritsche
Author-email: github@andresilaghi.com
License: MIT
Platform: UNKNOWN
Classifier: Programming Language :: Python :: 3
Classifier: License :: OSI Approved :: MIT License
Classifier: Operating System :: OS Independent
Requires-Dist: argparse
Requires-Dist: pika
Requires-Dist: pymongo
